<?xml version="1.0" encoding="UTF-8"?>
<objects serializationModel="Studio.02.01.00">
	<object class="Workspace" id="{91b3d145-5758-4f00-aa4b-6a1dbb56e7a1}">
		<relationship name="projectSettings">
			<destination>{f3fbadca-46e1-4814-b0bd-37d649a521c4}</destination>
		</relationship>
		<relationship name="changelist">
			<destination>{aba88f7d-ef26-46d9-8b91-007dee124e32}</destination>
		</relationship>
	</object>
	<object class="ProjectSettings" id="{f3fbadca-46e1-4814-b0bd-37d649a521c4}">
		<relationship name="activePlatform">
			<destination>{881eefda-5676-454f-8190-09b887a85a6b}</destination>
		</relationship>
	</object>
	<object class="WorkspaceChangelist" id="{aba88f7d-ef26-46d9-8b91-007dee124e32}" />
</objects>
